topsisLibrary/__init__.py
topsisLibrary/topsis.py
102003712-0.0.6.dist-info/METADATA
102003712-0.0.6.dist-info/WHEEL
102003712-0.0.6.dist-info/entry_points.txt
102003712-0.0.6.dist-info/top_level.txt
102003712-0.0.6.dist-info/RECORD
