Metadata-Version: 2.1
Name: 102003712
Version: 0.0.6
Summary: A Topsis Package
Home-page: UNKNOWN
Author: Garima Mittal
Author-email: gmittal1_be20@thapar.edu
License: UNKNOWN
Keywords: python,video,stream,video stream,camera stream,sockets
Platform: UNKNOWN
Classifier: Development Status :: 1 - Planning
Classifier: Intended Audience :: Developers
Classifier: Programming Language :: Python :: 3
Classifier: Operating System :: Unix
Classifier: Operating System :: MacOS :: MacOS X
Classifier: Operating System :: Microsoft :: Windows
Requires-Python: >=3.5
